licence_sdk_python/__init__.py
licence_sdk_python/check.py
licence_sdk_python/decorators.py
licence_sdk_python/filter.py
licence_sdk_python/fingerprint.py
licence_sdk_python/public_key.py
licence_sdk_python/types.py
licence_sdk_python/verify.py
licence_sdk_python/pyarmor_runtime_000000/__init__.py
licence_sdk_python/pyarmor_runtime_000000/pyarmor_runtime.so
licence_sdk_python-1.0.2.dist-info/METADATA
licence_sdk_python-1.0.2.dist-info/WHEEL
licence_sdk_python-1.0.2.dist-info/RECORD
