Metadata-Version: 2.4
Name: licence-sdk-python
Version: 1.0.2
Summary: 授权验证 SDK - 用于验证应用授权状态
Project-URL: Homepage, https://github.com/channing/licence
Project-URL: Repository, https://github.com/channing/licence
Project-URL: Documentation, https://github.com/channing/licence/tree/master/licence-sdk-python
Project-URL: Issues, https://github.com/channing/licence/issues
Author-email: channingxiao <channingxiao@gmail.com>
License: Proprietary
Keywords: authorization,licence,license,rsa,signature
Classifier: Development Status :: 4 - Beta
Classifier: Intended Audience :: Developers
Classifier: License :: Other/Proprietary License
Classifier: Programming Language :: Python :: 3
Classifier: Programming Language :: Python :: 3.10
Classifier: Programming Language :: Python :: 3.11
Classifier: Programming Language :: Python :: 3.12
Requires-Python: >=3.10
Requires-Dist: cryptography>=41.0.0
Requires-Dist: httpx>=0.25.0
Provides-Extra: dev
Requires-Dist: pyarmor>=8.0.0; extra == 'dev'
Requires-Dist: pytest-asyncio>=0.21.0; extra == 'dev'
Requires-Dist: pytest>=7.0.0; extra == 'dev'
